<?xml version="1.0"?>
<taxonomicCoverage><taxonomicClassification><taxonRankName>Kingdom</taxonRankName><taxonRankValue>Animalia</taxonRankValue><taxonomicClassification><taxonRankName>Phylum</taxonRankName><taxonRankValue>Chordata</taxonRankValue></taxonomicClassification><taxonomicClassification><taxonRankName>Phylum</taxonRankName><taxonRankValue>Cnidaria</taxonRankValue><taxonomicClassification><taxonRankName>CLASS</taxonRankName><taxonRankValue>Anthozoa</taxonRankValue><taxonomicClassification><taxonRankName>ORDER</taxonRankName><taxonRankValue>Scleractinia</taxonRankValue><taxonomicClassification><taxonRankName>FAMILY</taxonRankName><taxonRankValue>Poritidae</taxonRankValue><taxonomicClassification><taxonRankName>Genus</taxonRankName><taxonRankValue>Porites</taxonRankValue><taxonomicClassification><taxonRankName>Species</taxonRankName><taxonRankValue>Porites rus</taxonRankValue></taxonomicClassification></taxonomicClassification></taxonomicClassification></taxonomicClassification></taxonomicClassification></taxonomicClassification></taxonomicClassification></taxonomicCoverage>
